voynich/__init__.py
voynich-1.0.1.dist-info/licenses/LICENSE
voynich-1.0.1.dist-info/METADATA
voynich-1.0.1.dist-info/WHEEL
voynich-1.0.1.dist-info/top_level.txt
voynich-1.0.1.dist-info/RECORD
